banana_mcp/__init__.py
banana_mcp/__main__.py
banana_mcp/py.typed
banana_mcp/server.py
openrouter_banana_mcp-0.1.1.dist-info/METADATA
openrouter_banana_mcp-0.1.1.dist-info/WHEEL
openrouter_banana_mcp-0.1.1.dist-info/entry_points.txt
openrouter_banana_mcp-0.1.1.dist-info/RECORD
