Metadata-Version: 2.4
Name: openrouter-banana-mcp
Version: 0.1.1
Summary: MCP server that generates images via OpenRouter using google/gemini-3-pro-image-preview.
Author-email: sugarforever <william.1022@gmail.com>
Requires-Python: >=3.12
Requires-Dist: mcp>=1.0.0
Requires-Dist: python-dotenv>=1.0.1
Requires-Dist: requests>=2.31.0
